moneybhaiKV/__init__.py
moneybhaiKV-0.2.dist-info/LICENSE
moneybhaiKV-0.2.dist-info/METADATA
moneybhaiKV-0.2.dist-info/WHEEL
moneybhaiKV-0.2.dist-info/top_level.txt
moneybhaiKV-0.2.dist-info/RECORD
