Metadata-Version: 2.1
Name: moneybhaiKV
Version: 0.2
Summary: This is a simple package created to make my school life a lot easier... HOPE U WILL LIKE IT
Author: Yatharth Pandey
Author-email: pandeyyatharth2005@gmail.com
Keywords: python,school,easy,noob,school_project
Classifier: Development Status :: 1 - Planning
Classifier: Intended Audience :: Developers
Classifier: Programming Language :: Python :: 3
Classifier: Operating System :: Unix
Classifier: Operating System :: MacOS :: MacOS X
Classifier: Operating System :: Microsoft :: Windows
License-File: LICENSE
